{
  "meta": {
    "source_excel": "Расчет кинематики и системы нагружения (Восстановленный).xlsx",
    "sheet": "Лист1",
    "generated_at_utc": "2026-02-09T07:11:50.414131Z",
    "tolerance": 0.0001
  },
  "inputs": [
    {
      "cell": "C7",
      "name": "D1 =",
      "default": 287.0,
      "unit": "мм"
    },
    {
      "cell": "J7",
      "name": "D2 =",
      "default": 185.0,
      "unit": "мм"
    },
    {
      "cell": "O7",
      "name": "L1 =",
      "default": 290.0,
      "unit": "мм"
    },
    {
      "cell": "T7",
      "name": "Se =",
      "default": 450.0,
      "unit": "МПа"
    },
    {
      "cell": "C9",
      "name": "n1 =",
      "default": 2860.0,
      "unit": "об/мин"
    },
    {
      "cell": "J9",
      "name": "L =",
      "default": 3350.0,
      "unit": "мм"
    },
    {
      "cell": "O9",
      "name": "L2 =",
      "default": 845.0,
      "unit": "мм"
    },
    {
      "cell": "T9",
      "name": "σв =",
      "default": 450.0,
      "unit": "МПа"
    },
    {
      "cell": "C11",
      "name": "P =",
      "default": 3.0,
      "unit": "кВт"
    },
    {
      "cell": "J11",
      "name": "Q' =",
      "default": 8800.0,
      "unit": "Н"
    },
    {
      "cell": "O11",
      "name": "b1 =",
      "default": 330.0,
      "unit": "мм"
    },
    {
      "cell": "T11",
      "name": "ks =",
      "default": 0.8,
      "unit": ""
    },
    {
      "cell": "C13",
      "name": "μ =",
      "default": 0.5,
      "unit": ""
    },
    {
      "cell": "J13",
      "name": "M' =",
      "default": 600.0,
      "unit": "Нм"
    },
    {
      "cell": "O13",
      "name": "b2 =",
      "default": 400.0,
      "unit": "мм"
    },
    {
      "cell": "T13",
      "name": "kr =",
      "default": 0.8,
      "unit": ""
    },
    {
      "cell": "C15",
      "name": "kрем =",
      "default": 230.0,
      "unit": "Н/мм"
    },
    {
      "cell": "O15",
      "name": "s2 =",
      "default": 50.0,
      "unit": "мм"
    },
    {
      "cell": "T15",
      "name": "kt =",
      "default": 0.8,
      "unit": ""
    },
    {
      "cell": "C17",
      "name": "Fпров =",
      "default": 50.0,
      "unit": "Н"
    },
    {
      "cell": "O17",
      "name": "s3 =",
      "default": 50.0,
      "unit": "мм"
    },
    {
      "cell": "T17",
      "name": "krel =",
      "default": 0.8,
      "unit": ""
    },
    {
      "cell": "C19",
      "name": "Sэл =",
      "default": 10.0,
      "unit": "руб./кВтч"
    },
    {
      "cell": "O19",
      "name": "s4 =",
      "default": 1500.0,
      "unit": "мм"
    },
    {
      "cell": "T19",
      "name": "kf =",
      "default": 0.8,
      "unit": ""
    },
    {
      "cell": "J94",
      "name": "Fр =",
      "default": 4500.0,
      "unit": "Н"
    },
    {
      "cell": "N106",
      "name": "k",
      "default": 0.0,
      "unit": "=N106*$J$58"
    },
    {
      "cell": "N107",
      "name": "k",
      "default": 0.1,
      "unit": "=N107*$J$58"
    },
    {
      "cell": "N108",
      "name": "k",
      "default": 0.2,
      "unit": "=N108*$J$58"
    },
    {
      "cell": "N109",
      "name": "k",
      "default": 0.3,
      "unit": "=N109*$J$58"
    },
    {
      "cell": "N110",
      "name": "k",
      "default": 0.4,
      "unit": "=N110*$J$58"
    },
    {
      "cell": "N111",
      "name": "k",
      "default": 0.5,
      "unit": "=N111*$J$58"
    },
    {
      "cell": "N112",
      "name": "k",
      "default": 0.6,
      "unit": "=N112*$J$58"
    },
    {
      "cell": "N113",
      "name": "k",
      "default": 0.7,
      "unit": "=N113*$J$58"
    },
    {
      "cell": "N114",
      "name": "",
      "default": 0.8,
      "unit": "=N114*$J$58"
    },
    {
      "cell": "N115",
      "name": "",
      "default": 0.9,
      "unit": "=N115*$J$58"
    },
    {
      "cell": "N116",
      "name": "",
      "default": 1.0,
      "unit": "=N116*$J$58"
    },
    {
      "cell": "G125",
      "name": "14. Измеренный прогиб δизм, мм:",
      "default": 30.0,
      "unit": "мм"
    },
    {
      "cell": "E187",
      "name": "wст =",
      "default": 0.5,
      "unit": ""
    },
    {
      "cell": "O187",
      "name": "Sнач =",
      "default": 2011.0,
      "unit": "руб."
    },
    {
      "cell": "E189",
      "name": "wF =",
      "default": 0.5,
      "unit": ""
    },
    {
      "cell": "O189",
      "name": "Fнач =",
      "default": 25700.0,
      "unit": "Н"
    },
    {
      "cell": "E195",
      "name": "D1min =",
      "default": 185.0,
      "unit": "мм"
    },
    {
      "cell": "E197",
      "name": "D1max =",
      "default": 475.0,
      "unit": "мм"
    },
    {
      "cell": "E191",
      "name": "n1min =",
      "default": 500.0,
      "unit": "об/мин"
    },
    {
      "cell": "E193",
      "name": "n1max =",
      "default": 4000.0,
      "unit": "об/мин"
    },
    {
      "cell": "J191",
      "name": "D2min =",
      "default": 185.0,
      "unit": "мм"
    },
    {
      "cell": "J193",
      "name": "D2max =",
      "default": 475.0,
      "unit": "мм"
    },
    {
      "cell": "J195",
      "name": "Fpmin =",
      "default": 1.0,
      "unit": "Н"
    },
    {
      "cell": "J197",
      "name": "Fpmax =",
      "default": 4000.0,
      "unit": "Н"
    },
    {
      "cell": "J187",
      "name": "Tогранич =",
      "default": 7500.0,
      "unit": "H"
    }
  ],
  "formulas": [
    {
      "cell": "H38",
      "formula": "=PI()*(C7/1000)*(C9/60)",
      "deps": [
        "C7",
        "C9"
      ]
    },
    {
      "cell": "S38",
      "formula": "=C9*C7/J7",
      "deps": [
        "C7",
        "C9",
        "J7"
      ]
    },
    {
      "cell": "H45",
      "formula": "= C11*1000 / H38",
      "deps": [
        "C11",
        "H38"
      ]
    },
    {
      "cell": "T49",
      "formula": "=H45*(J7/2000)",
      "deps": [
        "H45",
        "J7"
      ]
    },
    {
      "cell": "H52",
      "formula": "=H45*(C7/2000)",
      "deps": [
        "C7",
        "H45"
      ]
    },
    {
      "cell": "J58",
      "formula": "=(\n J9 - (PI()/2)*(MAX(C7,J7)+MIN(C7,J7))\n + SQRT(\n     ( J9 - (PI()/2)*(MAX(C7,J7)+MIN(C7,J7)) )^2\n     - 2*( MAX(C7,J7) - MIN(C7,J7) )^2\n   )\n ) / 4",
      "deps": [
        "C7",
        "J7",
        "J9"
      ]
    },
    {
      "cell": "J64",
      "formula": "=PI() - 2*ASIN( ( MAX(C7,J7) - MIN(C7,J7) ) / ( 2*J58 ) )",
      "deps": [
        "C7",
        "J58",
        "J7"
      ]
    },
    {
      "cell": "J70",
      "formula": "=PI() + 2*ASIN( ( MAX(C7,J7) - MIN(C7,J7) ) / ( 2*J58 ) )",
      "deps": [
        "C7",
        "J58",
        "J7"
      ]
    },
    {
      "cell": "J76",
      "formula": "=J88/J82",
      "deps": [
        "J82",
        "J88"
      ]
    },
    {
      "cell": "U76",
      "formula": "=EXP(C13*J64)",
      "deps": [
        "C13",
        "J64"
      ]
    },
    {
      "cell": "J77",
      "formula": "=EXP(C13*J64)",
      "deps": [
        "C13",
        "J64"
      ]
    },
    {
      "cell": "J82",
      "formula": "=J94-H45/2",
      "deps": [
        "H45",
        "J94"
      ]
    },
    {
      "cell": "V82",
      "formula": "=H45/(U76-1)",
      "deps": [
        "H45",
        "U76"
      ]
    },
    {
      "cell": "J88",
      "formula": "=J94+H45/2",
      "deps": [
        "H45",
        "J94"
      ]
    },
    {
      "cell": "V88",
      "formula": "=U76*V82",
      "deps": [
        "U76",
        "V82"
      ]
    },
    {
      "cell": "V94",
      "formula": "=(V88+V82)/2",
      "deps": [
        "V82",
        "V88"
      ]
    },
    {
      "cell": "J100",
      "formula": "=J94/C15",
      "deps": [
        "C15",
        "J94"
      ]
    },
    {
      "cell": "O106",
      "formula": "=N106*$J$58",
      "deps": [
        "J58",
        "N106"
      ]
    },
    {
      "cell": "P106",
      "formula": "=J58",
      "deps": [
        "J58"
      ]
    },
    {
      "cell": "Q106",
      "formula": "=IF(OR(O106=0,P106=0),$J$100,SQRT(2*$J$100*O106*P106/$J$58))",
      "deps": [
        "J100",
        "J58",
        "O106",
        "P106"
      ]
    },
    {
      "cell": "O107",
      "formula": "=N107*$J$58",
      "deps": [
        "J58",
        "N107"
      ]
    },
    {
      "cell": "P107",
      "formula": "=$J$58 - O107",
      "deps": [
        "J58",
        "O107"
      ]
    },
    {
      "cell": "Q107",
      "formula": "=IF(OR(O107=0,P107=0),$J$100,SQRT(2*$J$100*O107*P107/$J$58))",
      "deps": [
        "J100",
        "J58",
        "O107",
        "P107"
      ]
    },
    {
      "cell": "O108",
      "formula": "=N108*$J$58",
      "deps": [
        "J58",
        "N108"
      ]
    },
    {
      "cell": "P108",
      "formula": "=$J$58 - O108",
      "deps": [
        "J58",
        "O108"
      ]
    },
    {
      "cell": "Q108",
      "formula": "=IF(OR(O108=0,P108=0),$J$100,SQRT(2*$J$100*O108*P108/$J$58))",
      "deps": [
        "J100",
        "J58",
        "O108",
        "P108"
      ]
    },
    {
      "cell": "O109",
      "formula": "=N109*$J$58",
      "deps": [
        "J58",
        "N109"
      ]
    },
    {
      "cell": "P109",
      "formula": "=$J$58 - O109",
      "deps": [
        "J58",
        "O109"
      ]
    },
    {
      "cell": "Q109",
      "formula": "=IF(OR(O109=0,P109=0),$J$100,SQRT(2*$J$100*O109*P109/$J$58))",
      "deps": [
        "J100",
        "J58",
        "O109",
        "P109"
      ]
    },
    {
      "cell": "O110",
      "formula": "=N110*$J$58",
      "deps": [
        "J58",
        "N110"
      ]
    },
    {
      "cell": "P110",
      "formula": "=$J$58 - O110",
      "deps": [
        "J58",
        "O110"
      ]
    },
    {
      "cell": "Q110",
      "formula": "=IF(OR(O110=0,P110=0),$J$100,SQRT(2*$J$100*O110*P110/$J$58))",
      "deps": [
        "J100",
        "J58",
        "O110",
        "P110"
      ]
    },
    {
      "cell": "O111",
      "formula": "=N111*$J$58",
      "deps": [
        "J58",
        "N111"
      ]
    },
    {
      "cell": "P111",
      "formula": "=$J$58 - O111",
      "deps": [
        "J58",
        "O111"
      ]
    },
    {
      "cell": "Q111",
      "formula": "=IF(OR(O111=0,P111=0),$J$100,SQRT(2*$J$100*O111*P111/$J$58))",
      "deps": [
        "J100",
        "J58",
        "O111",
        "P111"
      ]
    },
    {
      "cell": "O112",
      "formula": "=N112*$J$58",
      "deps": [
        "J58",
        "N112"
      ]
    },
    {
      "cell": "P112",
      "formula": "=$J$58 - O112",
      "deps": [
        "J58",
        "O112"
      ]
    },
    {
      "cell": "Q112",
      "formula": "=IF(OR(O112=0,P112=0),$J$100,SQRT(2*$J$100*O112*P112/$J$58))",
      "deps": [
        "J100",
        "J58",
        "O112",
        "P112"
      ]
    },
    {
      "cell": "O113",
      "formula": "=N113*$J$58",
      "deps": [
        "J58",
        "N113"
      ]
    },
    {
      "cell": "P113",
      "formula": "=$J$58 - O113",
      "deps": [
        "J58",
        "O113"
      ]
    },
    {
      "cell": "Q113",
      "formula": "=IF(OR(O113=0,P113=0),$J$100,SQRT(2*$J$100*O113*P113/$J$58))",
      "deps": [
        "J100",
        "J58",
        "O113",
        "P113"
      ]
    },
    {
      "cell": "O114",
      "formula": "=N114*$J$58",
      "deps": [
        "J58",
        "N114"
      ]
    },
    {
      "cell": "P114",
      "formula": "=$J$58 - O114",
      "deps": [
        "J58",
        "O114"
      ]
    },
    {
      "cell": "Q114",
      "formula": "=IF(OR(O114=0,P114=0),$J$100,SQRT(2*$J$100*O114*P114/$J$58))",
      "deps": [
        "J100",
        "J58",
        "O114",
        "P114"
      ]
    },
    {
      "cell": "O115",
      "formula": "=N115*$J$58",
      "deps": [
        "J58",
        "N115"
      ]
    },
    {
      "cell": "P115",
      "formula": "=$J$58 - O115",
      "deps": [
        "J58",
        "O115"
      ]
    },
    {
      "cell": "Q115",
      "formula": "=IF(OR(O115=0,P115=0),$J$100,SQRT(2*$J$100*O115*P115/$J$58))",
      "deps": [
        "J100",
        "J58",
        "O115",
        "P115"
      ]
    },
    {
      "cell": "O116",
      "formula": "=N116*$J$58",
      "deps": [
        "J58",
        "N116"
      ]
    },
    {
      "cell": "P116",
      "formula": "=$J$58 - O116",
      "deps": [
        "J58",
        "O116"
      ]
    },
    {
      "cell": "Q116",
      "formula": "=IF(OR(O116=0,P116=0),$J$100,SQRT(2*$J$100*O116*P116/$J$58))",
      "deps": [
        "J100",
        "J58",
        "O116",
        "P116"
      ]
    },
    {
      "cell": "J122",
      "formula": "= C17*J58/(4*J94)",
      "deps": [
        "C17",
        "J58",
        "J94"
      ]
    },
    {
      "cell": "H127",
      "formula": "= C17*J58/(4*G125)",
      "deps": [
        "C17",
        "G125",
        "J58"
      ]
    },
    {
      "cell": "J132",
      "formula": "=SQRT(\n  J88^2 +\n  J82^2 -\n  2*J88*J82*COS(\n    IF(J7=MAX(C7,J7), J70, J64)\n  )\n)",
      "deps": [
        "C7",
        "J64",
        "J7",
        "J70",
        "J82",
        "J88"
      ]
    },
    {
      "cell": "L141",
      "formula": "=IF(\n  (\n    -(\n      J132*((O11-O13)/J58)\n      *(O15+O17)\n      *(1-(O15+O17)/O19)\n      /1000\n     )\n    +SQRT(\n      (\n        SQRT(\n          (\n            J11*SQRT(1-((O11-O13)/J58)^2)\n            *(O15+O17)\n            *((O15+O17)+O19)\n            /O19\n            /1000\n          )^2\n          +\n          (\n            J11*((O11-O13)/J58)\n            *(O15+O17)\n            *(1-(O15+O17)/O19)\n            /1000\n          )^2\n        )\n        +\n        (T7*T11*T13*T15*T17/T19)*SQRT(3)/(2*T9)\n        *(J13-T49)\n      )^2\n      -\n      (\n        J132*SQRT(1-((O11-O13)/J58)^2)\n        *(O15+O17)\n        *((O15+O17)+O19)\n        /O19\n        /1000\n      )^2\n    )\n  )\n  /\n  (\n    ((O15+O17)*(1-O17/O19)-O15)/1000\n  )\n  > 0,\n\n  (\n    -(\n      J132*((O11-O13)/J58)\n      *(O15+O17)\n      *(1-(O15+O17)/O19)\n      /1000\n     )\n    +SQRT(\n      (\n        SQRT(\n          (\n            J11*SQRT(1-((O11-O13)/J58)^2)\n            *(O15+O17)\n            *((O15+O17)+O19)\n            /O19\n            /1000\n          )^2\n          +\n          (\n            J11*((O11-O13)/J58)\n            *(O15+O17)\n            *(1-(O15+O17)/O19)\n            /1000\n          )^2\n        )\n        +\n        (T7*T11*T13*T15*T17/T19)*SQRT(3)/(2*T9)\n        *(J13-T49)\n      )^2\n      -\n      (\n        J132*SQRT(1-((O11-O13)/J58)^2)\n        *(O15+O17)\n        *((O15+O17)+O19)\n        /O19\n        /1000\n      )^2\n    )\n  )\n  /\n  (\n    ((O15+O17)*(1-O17/O19)-O15)/1000\n  ),\n\n  (\n    -(\n      J132*((O11-O13)/J58)\n      *(O15+O17)\n      *(1-(O15+O17)/O19)\n      /1000\n     )\n    -SQRT(\n      (\n        SQRT(\n          (\n            J11*SQRT(1-((O11-O13)/J58)^2)\n            *(O15+O17)\n            *((O15+O17)+O19)\n            /O19\n            /1000\n          )^2\n          +\n          (\n            J11*((O11-O13)/J58)\n            *(O15+O17)\n            *(1-(O15+O17)/O19)\n            /1000\n          )^2\n        )\n        +\n        (T7*T11*T13*T15*T17/T19)*SQRT(3)/(2*T9)\n        *(J13-T49)\n      )^2\n      -\n      (\n        J132*SQRT(1-((O11-O13)/J58)^2)\n        *(O15+O17)\n        *((O15+O17)+O19)\n        /O19\n        /1000\n      )^2\n    )\n  )\n  /\n  (\n    ((O15+O17)*(1-O17/O19)-O15)/1000\n  )\n)",
      "deps": [
        "J11",
        "J13",
        "J132",
        "J58",
        "O11",
        "O13",
        "O15",
        "O17",
        "O19",
        "T11",
        "T13",
        "T15",
        "T17",
        "T19",
        "T49",
        "T7",
        "T9"
      ]
    },
    {
      "cell": "T168",
      "formula": "=10^7 / (S38 * 60)",
      "deps": [
        "S38"
      ]
    },
    {
      "cell": "J169",
      "formula": "=L141*0.1*O7/O9",
      "deps": [
        "L141",
        "O7",
        "O9"
      ]
    },
    {
      "cell": "T178",
      "formula": "=C19*C11*T168",
      "deps": [
        "C11",
        "C19",
        "T168"
      ]
    },
    {
      "cell": "J204",
      "formula": "=E187*(T178/O187)+E189*(L141/O189)",
      "deps": [
        "E187",
        "E189",
        "L141",
        "O187",
        "O189",
        "T178"
      ]
    }
  ],
  "outputs_required": [
    "J122",
    "J132",
    "L141",
    "J169",
    "T168",
    "T178",
    "J204"
  ],
  "outputs_terminal_suspected": [
    "H52",
    "J76",
    "J77",
    "V94",
    "Q106",
    "Q107",
    "Q108",
    "Q109",
    "Q110",
    "Q111",
    "Q112",
    "Q113",
    "Q114",
    "Q115",
    "Q116",
    "J122",
    "H127",
    "J169",
    "J204"
  ],
  "tables": {
    "kabs": {
      "k": {
        "range": "N106:N116"
      },
      "a": {
        "range": "O106:O116"
      },
      "b": {
        "range": "P106:P116"
      },
      "s": {
        "range": "Q106:Q116"
      }
    }
  },
  "solver": {
    "objective": "J204",
    "variables": [
      "C7",
      "J7",
      "C9",
      "J94"
    ],
    "constraints": [
      {
        "type": "le",
        "lhs": "C7",
        "rhs": "E197"
      },
      {
        "type": "ge",
        "lhs": "C7",
        "rhs": "E195"
      },
      {
        "type": "le",
        "lhs": "C9",
        "rhs": "E193"
      },
      {
        "type": "ge",
        "lhs": "C9",
        "rhs": "E191"
      },
      {
        "type": "le",
        "lhs": "J7",
        "rhs": "J193"
      },
      {
        "type": "ge",
        "lhs": "J7",
        "rhs": "J191"
      },
      {
        "type": "le",
        "lhs": "J76",
        "rhs": "J77"
      },
      {
        "type": "le",
        "lhs": "J82",
        "rhs": "J187"
      },
      {
        "type": "ge",
        "lhs": "J82",
        "rhs": 1
      },
      {
        "type": "le",
        "lhs": "J88",
        "rhs": "J187"
      },
      {
        "type": "le",
        "lhs": "J94",
        "rhs": "J197"
      },
      {
        "type": "ge",
        "lhs": "J94",
        "rhs": "J195"
      }
    ],
    "soft_violation_cap_rel": 0.05
  }
}
